README.md
setup.cfg
setup.py
tensorflow_murmur/__init__.py
tensorflow_murmur.egg-info/PKG-INFO
tensorflow_murmur.egg-info/SOURCES.txt
tensorflow_murmur.egg-info/dependency_links.txt
tensorflow_murmur.egg-info/requires.txt
tensorflow_murmur.egg-info/top_level.txt
tensorflow_murmur/layers/__init__.py
tensorflow_murmur/layers/embeddings.py
tensorflow_murmur/layers/layers.py
tensorflow_murmur/layers/preprocessing.py
tensorflow_murmur/losses/__init__.py
tensorflow_murmur/losses/losses.py
tensorflow_murmur/metrics/__init__.py
tensorflow_murmur/metrics/metrics.py