Metadata-Version: 2.1
Name: tensorflow-murmur
Version: 0.0.12
Summary: This is a small addons module for tensorflow
Home-page: https://pypi.org/project/tensorflow-murmur/
Author: Ivan V. Savkin
Author-email: i.v.savkin2020@yandex.ru
Project-URL: GitHub, https://github.com/jordmundgand/tensorflow_murmur
Keywords: tf addons
Classifier: Programming Language :: Python :: 3.11
Classifier: License :: OSI Approved :: MIT License
Classifier: Operating System :: OS Independent
Requires-Python: >=3.8
